{
    "data": {
        "name": {
            "__typename": "Name",
            "knownFor": {
                "edges": [
                    {
                        "node": {
                            "title": {
                                "__typename": "Title",
                                "id": "tt0110912",
                                "titleText": {
                                    "text": "Pulp Fiction",
                                    "isOriginalTitle": true
                                },
                                "originalTitleText": {
                                    "text": "Pulp Fiction",
                                    "isOriginalTitle": true
                                },
                                "releaseYear": {
                                    "__typename": "YearRange",
                                    "year": 1994,
                                    "endYear": null
                                },
                                "releaseDate": {
                                    "__typename": "ReleaseDate",
                                    "month": 10,
                                    "day": 14,
                                    "year": 1994,
                                    "country": {
                                        "id": "US"
                                    },
                                    "restriction": null,
                                    "attributes": [],
                                    "displayableProperty": {
                                        "qualifiersInMarkdownList": null
                                    }
                                },
                                "titleType": {
                                    "__typename": "TitleType",
                                    "id": "movie",
                                    "text": "Movie",
                                    "categories": [
                                        {
                                            "id": "movie",
                                            "text": "Movie",
                                            "value": "movie"
                                        }
                                    ],
                                    "canHaveEpisodes": false,
                                    "isEpisode": false,
                                    "isSeries": false,
                                    "displayableProperty": {
                                        "value": {
                                            "plainText": ""
                                        }
                                    }
                                },
                                "primaryImage": {
                                    "__typename": "Image",
                                    "id": "rm1959546112",
                                    "url": "https://m.media-amazon.com/images/M/MV5BYTViYTE3ZGQtNDBlMC00ZTAyLTkyODMtZGRiZDg0MjA2YThkXkEyXkFqcGc@._V1_.jpg",
                                    "height": 1536,
                                    "width": 1055
                                },
                                "ratingsSummary": {
                                    "aggregateRating": 8.8
                                }
                            },
                            "credit": {
                                "__typename": "Cast",
                                "category": {
                                    "id": "actor",
                                    "text": "Actor"
                                },
                                "characters": [
                                    {
                                        "name": "Jules Winnfield"
                                    }
                                ]
                            }
                        }
                    },
                    {
                        "node": {
                            "title": {
                                "__typename": "Title",
                                "id": "tt3460252",
                                "titleText": {
                                    "text": "The Hateful Eight",
                                    "isOriginalTitle": true
                                },
                                "originalTitleText": {
                                    "text": "The Hateful Eight",
                                    "isOriginalTitle": true
                                },
                                "releaseYear": {
                                    "__typename": "YearRange",
                                    "year": 2015,
                                    "endYear": null
                                },
                                "releaseDate": {
                                    "__typename": "ReleaseDate",
                                    "month": 12,
                                    "day": 30,
                                    "year": 2015,
                                    "country": {
                                        "id": "US"
                                    },
                                    "restriction": null,
                                    "attributes": [],
                                    "displayableProperty": {
                                        "qualifiersInMarkdownList": null
                                    }
                                },
                                "titleType": {
                                    "__typename": "TitleType",
                                    "id": "movie",
                                    "text": "Movie",
                                    "categories": [
                                        {
                                            "id": "movie",
                                            "text": "Movie",
                                            "value": "movie"
                                        }
                                    ],
                                    "canHaveEpisodes": false,
                                    "isEpisode": false,
                                    "isSeries": false,
                                    "displayableProperty": {
                                        "value": {
                                            "plainText": ""
                                        }
                                    }
                                },
                                "primaryImage": {
                                    "__typename": "Image",
                                    "id": "rm2736055040",
                                    "url": "https://m.media-amazon.com/images/M/MV5BMjA1MTc1NTg5NV5BMl5BanBnXkFtZTgwOTM2MDEzNzE@._V1_.jpg",
                                    "height": 2048,
                                    "width": 1382
                                },
                                "ratingsSummary": {
                                    "aggregateRating": 7.8
                                }
                            },
                            "credit": {
                                "__typename": "Cast",
                                "category": {
                                    "id": "actor",
                                    "text": "Actor"
                                },
                                "characters": [
                                    {
                                        "name": "Major Marquis Warren"
                                    }
                                ]
                            }
                        }
                    },
                    {
                        "node": {
                            "title": {
                                "__typename": "Title",
                                "id": "tt2802144",
                                "titleText": {
                                    "text": "Kingsman: The Secret Service",
                                    "isOriginalTitle": true
                                },
                                "originalTitleText": {
                                    "text": "Kingsman: The Secret Service",
                                    "isOriginalTitle": true
                                },
                                "releaseYear": {
                                    "__typename": "YearRange",
                                    "year": 2014,
                                    "endYear": null
                                },
                                "releaseDate": {
                                    "__typename": "ReleaseDate",
                                    "month": 2,
                                    "day": 13,
                                    "year": 2015,
                                    "country": {
                                        "id": "US"
                                    },
                                    "restriction": null,
                                    "attributes": [],
                                    "displayableProperty": {
                                        "qualifiersInMarkdownList": null
                                    }
                                },
                                "titleType": {
                                    "__typename": "TitleType",
                                    "id": "movie",
                                    "text": "Movie",
                                    "categories": [
                                        {
                                            "id": "movie",
                                            "text": "Movie",
                                            "value": "movie"
                                        }
                                    ],
                                    "canHaveEpisodes": false,
                                    "isEpisode": false,
                                    "isSeries": false,
                                    "displayableProperty": {
                                        "value": {
                                            "plainText": ""
                                        }
                                    }
                                },
                                "primaryImage": {
                                    "__typename": "Image",
                                    "id": "rm1450692609",
                                    "url": "https://m.media-amazon.com/images/M/MV5BODk1MTYwNTAtYmI5Zi00OWYyLWE0MzQtOWE4NDIxZmU2MjMwXkEyXkFqcGc@._V1_.jpg",
                                    "height": 3000,
                                    "width": 2000
                                },
                                "ratingsSummary": {
                                    "aggregateRating": 7.7
                                }
                            },
                            "credit": {
                                "__typename": "Cast",
                                "category": {
                                    "id": "actor",
                                    "text": "Actor"
                                },
                                "characters": [
                                    {
                                        "name": "Valentine"
                                    }
                                ]
                            }
                        }
                    },
                    {
                        "node": {
                            "title": {
                                "__typename": "Title",
                                "id": "tt4154664",
                                "titleText": {
                                    "text": "Captain Marvel",
                                    "isOriginalTitle": true
                                },
                                "originalTitleText": {
                                    "text": "Captain Marvel",
                                    "isOriginalTitle": true
                                },
                                "releaseYear": {
                                    "__typename": "YearRange",
                                    "year": 2019,
                                    "endYear": null
                                },
                                "releaseDate": {
                                    "__typename": "ReleaseDate",
                                    "month": 3,
                                    "day": 8,
                                    "year": 2019,
                                    "country": {
                                        "id": "US"
                                    },
                                    "restriction": null,
                                    "attributes": [],
                                    "displayableProperty": {
                                        "qualifiersInMarkdownList": null
                                    }
                                },
                                "titleType": {
                                    "__typename": "TitleType",
                                    "id": "movie",
                                    "text": "Movie",
                                    "categories": [
                                        {
                                            "id": "movie",
                                            "text": "Movie",
                                            "value": "movie"
                                        }
                                    ],
                                    "canHaveEpisodes": false,
                                    "isEpisode": false,
                                    "isSeries": false,
                                    "displayableProperty": {
                                        "value": {
                                            "plainText": ""
                                        }
                                    }
                                },
                                "primaryImage": {
                                    "__typename": "Image",
                                    "id": "rm123368960",
                                    "url": "https://m.media-amazon.com/images/M/MV5BZDI1NGU2ODAtNzBiNy00MWY5LWIyMGEtZjUxZjUwZmZiNjBlXkEyXkFqcGc@._V1_.jpg",
                                    "height": 2500,
                                    "width": 1688
                                },
                                "ratingsSummary": {
                                    "aggregateRating": 6.7
                                }
                            },
                            "credit": {
                                "__typename": "Cast",
                                "category": {
                                    "id": "actor",
                                    "text": "Actor"
                                },
                                "characters": [
                                    {
                                        "name": "Nick Fury"
                                    }
                                ]
                            }
                        }
                    },
                    {
                        "node": {
                            "title": {
                                "__typename": "Title",
                                "id": "tt0417148",
                                "titleText": {
                                    "text": "Snakes on a Plane",
                                    "isOriginalTitle": true
                                },
                                "originalTitleText": {
                                    "text": "Snakes on a Plane",
                                    "isOriginalTitle": true
                                },
                                "releaseYear": {
                                    "__typename": "YearRange",
                                    "year": 2006,
                                    "endYear": null
                                },
                                "releaseDate": {
                                    "__typename": "ReleaseDate",
                                    "month": 8,
                                    "day": 18,
                                    "year": 2006,
                                    "country": {
                                        "id": "US"
                                    },
                                    "restriction": null,
                                    "attributes": [],
                                    "displayableProperty": {
                                        "qualifiersInMarkdownList": null
                                    }
                                },
                                "titleType": {
                                    "__typename": "TitleType",
                                    "id": "movie",
                                    "text": "Movie",
                                    "categories": [
                                        {
                                            "id": "movie",
                                            "text": "Movie",
                                            "value": "movie"
                                        }
                                    ],
                                    "canHaveEpisodes": false,
                                    "isEpisode": false,
                                    "isSeries": false,
                                    "displayableProperty": {
                                        "value": {
                                            "plainText": ""
                                        }
                                    }
                                },
                                "primaryImage": {
                                    "__typename": "Image",
                                    "id": "rm753208064",
                                    "url": "https://m.media-amazon.com/images/M/MV5BMThjYjk2MDItYTFiNS00N2I1LTgwYjktMWM4ODFjYTczYmUxXkEyXkFqcGc@._V1_.jpg",
                                    "height": 815,
                                    "width": 550
                                },
                                "ratingsSummary": {
                                    "aggregateRating": 5.5
                                }
                            },
                            "credit": {
                                "__typename": "Cast",
                                "category": {
                                    "id": "actor",
                                    "text": "Actor"
                                },
                                "characters": [
                                    {
                                        "name": "Neville Flynn"
                                    }
                                ]
                            }
                        }
                    },
                    {
                        "node": {
                            "title": {
                                "__typename": "Title",
                                "id": "tt0120768",
                                "titleText": {
                                    "text": "The Negotiator",
                                    "isOriginalTitle": true
                                },
                                "originalTitleText": {
                                    "text": "The Negotiator",
                                    "isOriginalTitle": true
                                },
                                "releaseYear": {
                                    "__typename": "YearRange",
                                    "year": 1998,
                                    "endYear": null
                                },
                                "releaseDate": {
                                    "__typename": "ReleaseDate",
                                    "month": 7,
                                    "day": 29,
                                    "year": 1998,
                                    "country": {
                                        "id": "US"
                                    },
                                    "restriction": null,
                                    "attributes": [],
                                    "displayableProperty": {
                                        "qualifiersInMarkdownList": null
                                    }
                                },
                                "titleType": {
                                    "__typename": "TitleType",
                                    "id": "movie",
                                    "text": "Movie",
                                    "categories": [
                                        {
                                            "id": "movie",
                                            "text": "Movie",
                                            "value": "movie"
                                        }
                                    ],
                                    "canHaveEpisodes": false,
                                    "isEpisode": false,
                                    "isSeries": false,
                                    "displayableProperty": {
                                        "value": {
                                            "plainText": ""
                                        }
                                    }
                                },
                                "primaryImage": {
                                    "__typename": "Image",
                                    "id": "rm2723625216",
                                    "url": "https://m.media-amazon.com/images/M/MV5BNTBjZDM3NzctOGE2YS00NDZiLTk4ZWMtY2IwOWI5ZTE4ZDc0XkEyXkFqcGc@._V1_.jpg",
                                    "height": 1500,
                                    "width": 1000
                                },
                                "ratingsSummary": {
                                    "aggregateRating": 7.3
                                }
                            },
                            "credit": {
                                "__typename": "Cast",
                                "category": {
                                    "id": "actor",
                                    "text": "Actor"
                                },
                                "characters": [
                                    {
                                        "name": "Danny Roman"
                                    }
                                ]
                            }
                        }
                    },
                    {
                        "node": {
                            "title": {
                                "__typename": "Title",
                                "id": "tt0119396",
                                "titleText": {
                                    "text": "Jackie Brown",
                                    "isOriginalTitle": true
                                },
                                "originalTitleText": {
                                    "text": "Jackie Brown",
                                    "isOriginalTitle": true
                                },
                                "releaseYear": {
                                    "__typename": "YearRange",
                                    "year": 1997,
                                    "endYear": null
                                },
                                "releaseDate": {
                                    "__typename": "ReleaseDate",
                                    "month": 12,
                                    "day": 25,
                                    "year": 1997,
                                    "country": {
                                        "id": "US"
                                    },
                                    "restriction": null,
                                    "attributes": [],
                                    "displayableProperty": {
                                        "qualifiersInMarkdownList": null
                                    }
                                },
                                "titleType": {
                                    "__typename": "TitleType",
                                    "id": "movie",
                                    "text": "Movie",
                                    "categories": [
                                        {
                                            "id": "movie",
                                            "text": "Movie",
                                            "value": "movie"
                                        }
                                    ],
                                    "canHaveEpisodes": false,
                                    "isEpisode": false,
                                    "isSeries": false,
                                    "displayableProperty": {
                                        "value": {
                                            "plainText": ""
                                        }
                                    }
                                },
                                "primaryImage": {
                                    "__typename": "Image",
                                    "id": "rm2234134784",
                                    "url": "https://m.media-amazon.com/images/M/MV5BZmUxZjY3MDktNGI5NS00MTQ5LWE0YWItZWQzNmZhNjhkZDYyXkEyXkFqcGc@._V1_.jpg",
                                    "height": 1755,
                                    "width": 1200
                                },
                                "ratingsSummary": {
                                    "aggregateRating": 7.5
                                }
                            },
                            "credit": {
                                "__typename": "Cast",
                                "category": {
                                    "id": "actor",
                                    "text": "Actor"
                                },
                                "characters": [
                                    {
                                        "name": "Ordell Robbie"
                                    }
                                ]
                            }
                        }
                    },
                    {
                        "node": {
                            "title": {
                                "__typename": "Title",
                                "id": "tt0217869",
                                "titleText": {
                                    "text": "Unbreakable",
                                    "isOriginalTitle": true
                                },
                                "originalTitleText": {
                                    "text": "Unbreakable",
                                    "isOriginalTitle": true
                                },
                                "releaseYear": {
                                    "__typename": "YearRange",
                                    "year": 2000,
                                    "endYear": null
                                },
                                "releaseDate": {
                                    "__typename": "ReleaseDate",
                                    "month": 11,
                                    "day": 22,
                                    "year": 2000,
                                    "country": {
                                        "id": "US"
                                    },
                                    "restriction": null,
                                    "attributes": [],
                                    "displayableProperty": {
                                        "qualifiersInMarkdownList": null
                                    }
                                },
                                "titleType": {
                                    "__typename": "TitleType",
                                    "id": "movie",
                                    "text": "Movie",
                                    "categories": [
                                        {
                                            "id": "movie",
                                            "text": "Movie",
                                            "value": "movie"
                                        }
                                    ],
                                    "canHaveEpisodes": false,
                                    "isEpisode": false,
                                    "isSeries": false,
                                    "displayableProperty": {
                                        "value": {
                                            "plainText": ""
                                        }
                                    }
                                },
                                "primaryImage": {
                                    "__typename": "Image",
                                    "id": "rm1799166208",
                                    "url": "https://m.media-amazon.com/images/M/MV5BZWNmMGYwMDQtNGIxMS00MzMzLTlhNmItYzllN2M2M2EwMTZmXkEyXkFqcGc@._V1_.jpg",
                                    "height": 3210,
                                    "width": 2170
                                },
                                "ratingsSummary": {
                                    "aggregateRating": 7.3
                                }
                            },
                            "credit": {
                                "__typename": "Cast",
                                "category": {
                                    "id": "actor",
                                    "text": "Actor"
                                },
                                "characters": [
                                    {
                                        "name": "Elijah Price"
                                    }
                                ]
                            }
                        }
                    },
                    {
                        "node": {
                            "title": {
                                "__typename": "Title",
                                "id": "tt0117913",
                                "titleText": {
                                    "text": "A Time to Kill",
                                    "isOriginalTitle": true
                                },
                                "originalTitleText": {
                                    "text": "A Time to Kill",
                                    "isOriginalTitle": true
                                },
                                "releaseYear": {
                                    "__typename": "YearRange",
                                    "year": 1996,
                                    "endYear": null
                                },
                                "releaseDate": {
                                    "__typename": "ReleaseDate",
                                    "month": 7,
                                    "day": 24,
                                    "year": 1996,
                                    "country": {
                                        "id": "US"
                                    },
                                    "restriction": null,
                                    "attributes": [],
                                    "displayableProperty": {
                                        "qualifiersInMarkdownList": null
                                    }
                                },
                                "titleType": {
                                    "__typename": "TitleType",
                                    "id": "movie",
                                    "text": "Movie",
                                    "categories": [
                                        {
                                            "id": "movie",
                                            "text": "Movie",
                                            "value": "movie"
                                        }
                                    ],
                                    "canHaveEpisodes": false,
                                    "isEpisode": false,
                                    "isSeries": false,
                                    "displayableProperty": {
                                        "value": {
                                            "plainText": ""
                                        }
                                    }
                                },
                                "primaryImage": {
                                    "__typename": "Image",
                                    "id": "rm1796824833",
                                    "url": "https://m.media-amazon.com/images/M/MV5BYmNiYzY1N2ItZDZiNC00ZGMyLWJlZjktZDE1MDI3NDBlYjE5XkEyXkFqcGc@._V1_.jpg",
                                    "height": 2260,
                                    "width": 1519
                                },
                                "ratingsSummary": {
                                    "aggregateRating": 7.5
                                }
                            },
                            "credit": {
                                "__typename": "Cast",
                                "category": {
                                    "id": "actor",
                                    "text": "Actor"
                                },
                                "characters": [
                                    {
                                        "name": "Carl Lee Hailey"
                                    }
                                ]
                            }
                        }
                    },
                    {
                        "node": {
                            "title": {
                                "__typename": "Title",
                                "id": "tt0393162",
                                "titleText": {
                                    "text": "Coach Carter",
                                    "isOriginalTitle": true
                                },
                                "originalTitleText": {
                                    "text": "Coach Carter",
                                    "isOriginalTitle": true
                                },
                                "releaseYear": {
                                    "__typename": "YearRange",
                                    "year": 2005,
                                    "endYear": null
                                },
                                "releaseDate": {
                                    "__typename": "ReleaseDate",
                                    "month": 1,
                                    "day": 14,
                                    "year": 2005,
                                    "country": {
                                        "id": "US"
                                    },
                                    "restriction": null,
                                    "attributes": [],
                                    "displayableProperty": {
                                        "qualifiersInMarkdownList": null
                                    }
                                },
                                "titleType": {
                                    "__typename": "TitleType",
                                    "id": "movie",
                                    "text": "Movie",
                                    "categories": [
                                        {
                                            "id": "movie",
                                            "text": "Movie",
                                            "value": "movie"
                                        }
                                    ],
                                    "canHaveEpisodes": false,
                                    "isEpisode": false,
                                    "isSeries": false,
                                    "displayableProperty": {
                                        "value": {
                                            "plainText": ""
                                        }
                                    }
                                },
                                "primaryImage": {
                                    "__typename": "Image",
                                    "id": "rm2796356096",
                                    "url": "https://m.media-amazon.com/images/M/MV5BNjk0M2Y4ZTUtNzA3MS00MWYwLThmYjktMmYzNzVkYzQ3NmFlXkEyXkFqcGc@._V1_.jpg",
                                    "height": 3000,
                                    "width": 2025
                                },
                                "ratingsSummary": {
                                    "aggregateRating": 7.3
                                }
                            },
                            "credit": {
                                "__typename": "Cast",
                                "category": {
                                    "id": "actor",
                                    "text": "Actor"
                                },
                                "characters": [
                                    {
                                        "name": "Coach Ken Carter"
                                    }
                                ]
                            }
                        }
                    },
                    {
                        "node": {
                            "title": {
                                "__typename": "Title",
                                "id": "tt0257076",
                                "titleText": {
                                    "text": "S.W.A.T.",
                                    "isOriginalTitle": true
                                },
                                "originalTitleText": {
                                    "text": "S.W.A.T.",
                                    "isOriginalTitle": true
                                },
                                "releaseYear": {
                                    "__typename": "YearRange",
                                    "year": 2003,
                                    "endYear": null
                                },
                                "releaseDate": {
                                    "__typename": "ReleaseDate",
                                    "month": 8,
                                    "day": 8,
                                    "year": 2003,
                                    "country": {
                                        "id": "US"
                                    },
                                    "restriction": null,
                                    "attributes": [],
                                    "displayableProperty": {
                                        "qualifiersInMarkdownList": null
                                    }
                                },
                                "titleType": {
                                    "__typename": "TitleType",
                                    "id": "movie",
                                    "text": "Movie",
                                    "categories": [
                                        {
                                            "id": "movie",
                                            "text": "Movie",
                                            "value": "movie"
                                        }
                                    ],
                                    "canHaveEpisodes": false,
                                    "isEpisode": false,
                                    "isSeries": false,
                                    "displayableProperty": {
                                        "value": {
                                            "plainText": ""
                                        }
                                    }
                                },
                                "primaryImage": {
                                    "__typename": "Image",
                                    "id": "rm229912577",
                                    "url": "https://m.media-amazon.com/images/M/MV5BNmMwYjNhYTEtNGM3ZS00ZTNjLWE1ZWItOWU0MGU4YTUwNjk0XkEyXkFqcGc@._V1_.jpg",
                                    "height": 1000,
                                    "width": 674
                                },
                                "ratingsSummary": {
                                    "aggregateRating": 6.1
                                }
                            },
                            "credit": {
                                "__typename": "Cast",
                                "category": {
                                    "id": "actor",
                                    "text": "Actor"
                                },
                                "characters": [
                                    {
                                        "name": "Sgt. Dan 'Hondo' Harrelson"
                                    }
                                ]
                            }
                        }
                    },
                    {
                        "node": {
                            "title": {
                                "__typename": "Title",
                                "id": "tt0116908",
                                "titleText": {
                                    "text": "The Long Kiss Goodnight",
                                    "isOriginalTitle": true
                                },
                                "originalTitleText": {
                                    "text": "The Long Kiss Goodnight",
                                    "isOriginalTitle": true
                                },
                                "releaseYear": {
                                    "__typename": "YearRange",
                                    "year": 1996,
                                    "endYear": null
                                },
                                "releaseDate": {
                                    "__typename": "ReleaseDate",
                                    "month": 10,
                                    "day": 11,
                                    "year": 1996,
                                    "country": {
                                        "id": "US"
                                    },
                                    "restriction": null,
                                    "attributes": [],
                                    "displayableProperty": {
                                        "qualifiersInMarkdownList": null
                                    }
                                },
                                "titleType": {
                                    "__typename": "TitleType",
                                    "id": "movie",
                                    "text": "Movie",
                                    "categories": [
                                        {
                                            "id": "movie",
                                            "text": "Movie",
                                            "value": "movie"
                                        }
                                    ],
                                    "canHaveEpisodes": false,
                                    "isEpisode": false,
                                    "isSeries": false,
                                    "displayableProperty": {
                                        "value": {
                                            "plainText": ""
                                        }
                                    }
                                },
                                "primaryImage": {
                                    "__typename": "Image",
                                    "id": "rm375468544",
                                    "url": "https://m.media-amazon.com/images/M/MV5BZjJmNzZjODktNmNhMy00NDZiLWIwNGUtM2NjYWNhZWU4YTY1XkEyXkFqcGc@._V1_.jpg",
                                    "height": 855,
                                    "width": 550
                                },
                                "ratingsSummary": {
                                    "aggregateRating": 6.8
                                }
                            },
                            "credit": {
                                "__typename": "Cast",
                                "category": {
                                    "id": "actor",
                                    "text": "Actor"
                                },
                                "characters": [
                                    {
                                        "name": "Mitch Henessey"
                                    }
                                ]
                            }
                        }
                    },
                    {
                        "node": {
                            "title": {
                                "__typename": "Title",
                                "id": "tt1843866",
                                "titleText": {
                                    "text": "Captain America: The Winter Soldier",
                                    "isOriginalTitle": true
                                },
                                "originalTitleText": {
                                    "text": "Captain America: The Winter Soldier",
                                    "isOriginalTitle": true
                                },
                                "releaseYear": {
                                    "__typename": "YearRange",
                                    "year": 2014,
                                    "endYear": null
                                },
                                "releaseDate": {
                                    "__typename": "ReleaseDate",
                                    "month": 4,
                                    "day": 4,
                                    "year": 2014,
                                    "country": {
                                        "id": "US"
                                    },
                                    "restriction": null,
                                    "attributes": [],
                                    "displayableProperty": {
                                        "qualifiersInMarkdownList": null
                                    }
                                },
                                "titleType": {
                                    "__typename": "TitleType",
                                    "id": "movie",
                                    "text": "Movie",
                                    "categories": [
                                        {
                                            "id": "movie",
                                            "text": "Movie",
                                            "value": "movie"
                                        }
                                    ],
                                    "canHaveEpisodes": false,
                                    "isEpisode": false,
                                    "isSeries": false,
                                    "displayableProperty": {
                                        "value": {
                                            "plainText": ""
                                        }
                                    }
                                },
                                "primaryImage": {
                                    "__typename": "Image",
                                    "id": "rm2928226816",
                                    "url": "https://m.media-amazon.com/images/M/MV5BNWY1NjFmNDItZDhmOC00NjI1LWE0ZDItMTM0MjBjZThiOTQ2XkEyXkFqcGc@._V1_.jpg",
                                    "height": 2500,
                                    "width": 1688
                                },
                                "ratingsSummary": {
                                    "aggregateRating": 7.7
                                }
                            },
                            "credit": {
                                "__typename": "Cast",
                                "category": {
                                    "id": "actor",
                                    "text": "Actor"
                                },
                                "characters": [
                                    {
                                        "name": "Nick Fury"
                                    }
                                ]
                            }
                        }
                    },
                    {
                        "node": {
                            "title": {
                                "__typename": "Title",
                                "id": "tt0489099",
                                "titleText": {
                                    "text": "Jumper",
                                    "isOriginalTitle": true
                                },
                                "originalTitleText": {
                                    "text": "Jumper",
                                    "isOriginalTitle": true
                                },
                                "releaseYear": {
                                    "__typename": "YearRange",
                                    "year": 2008,
                                    "endYear": null
                                },
                                "releaseDate": {
                                    "__typename": "ReleaseDate",
                                    "month": 2,
                                    "day": 14,
                                    "year": 2008,
                                    "country": {
                                        "id": "US"
                                    },
                                    "restriction": null,
                                    "attributes": [],
                                    "displayableProperty": {
                                        "qualifiersInMarkdownList": null
                                    }
                                },
                                "titleType": {
                                    "__typename": "TitleType",
                                    "id": "movie",
                                    "text": "Movie",
                                    "categories": [
                                        {
                                            "id": "movie",
                                            "text": "Movie",
                                            "value": "movie"
                                        }
                                    ],
                                    "canHaveEpisodes": false,
                                    "isEpisode": false,
                                    "isSeries": false,
                                    "displayableProperty": {
                                        "value": {
                                            "plainText": ""
                                        }
                                    }
                                },
                                "primaryImage": {
                                    "__typename": "Image",
                                    "id": "rm3945658113",
                                    "url": "https://m.media-amazon.com/images/M/MV5BMWQ3NjA3NTYtNDJiYi00ZTE0LWFmNzMtZjc0NTUxNjk2YTFkXkEyXkFqcGc@._V1_.jpg",
                                    "height": 1597,
                                    "width": 1080
                                },
                                "ratingsSummary": {
                                    "aggregateRating": 6.1
                                }
                            },
                            "credit": {
                                "__typename": "Cast",
                                "category": {
                                    "id": "actor",
                                    "text": "Actor"
                                },
                                "characters": [
                                    {
                                        "name": "Roland"
                                    }
                                ]
                            }
                        }
                    },
                    {
                        "node": {
                            "title": {
                                "__typename": "Title",
                                "id": "tt0848228",
                                "titleText": {
                                    "text": "The Avengers",
                                    "isOriginalTitle": true
                                },
                                "originalTitleText": {
                                    "text": "The Avengers",
                                    "isOriginalTitle": true
                                },
                                "releaseYear": {
                                    "__typename": "YearRange",
                                    "year": 2012,
                                    "endYear": null
                                },
                                "releaseDate": {
                                    "__typename": "ReleaseDate",
                                    "month": 5,
                                    "day": 4,
                                    "year": 2012,
                                    "country": {
                                        "id": "US"
                                    },
                                    "restriction": null,
                                    "attributes": [],
                                    "displayableProperty": {
                                        "qualifiersInMarkdownList": null
                                    }
                                },
                                "titleType": {
                                    "__typename": "TitleType",
                                    "id": "movie",
                                    "text": "Movie",
                                    "categories": [
                                        {
                                            "id": "movie",
                                            "text": "Movie",
                                            "value": "movie"
                                        }
                                    ],
                                    "canHaveEpisodes": false,
                                    "isEpisode": false,
                                    "isSeries": false,
                                    "displayableProperty": {
                                        "value": {
                                            "plainText": ""
                                        }
                                    }
                                },
                                "primaryImage": {
                                    "__typename": "Image",
                                    "id": "rm3955117056",
                                    "url": "https://m.media-amazon.com/images/M/MV5BNGE0YTVjNzUtNzJjOS00NGNlLTgxMzctZTY4YTE1Y2Y1ZTU4XkEyXkFqcGc@._V1_.jpg",
                                    "height": 1184,
                                    "width": 800
                                },
                                "ratingsSummary": {
                                    "aggregateRating": 8
                                }
                            },
                            "credit": {
                                "__typename": "Cast",
                                "category": {
                                    "id": "actor",
                                    "text": "Actor"
                                },
                                "characters": [
                                    {
                                        "name": "Nick Fury"
                                    }
                                ]
                            }
                        }
                    },
                    {
                        "node": {
                            "title": {
                                "__typename": "Title",
                                "id": "tt1321511",
                                "titleText": {
                                    "text": "Oldboy",
                                    "isOriginalTitle": true
                                },
                                "originalTitleText": {
                                    "text": "Oldboy",
                                    "isOriginalTitle": true
                                },
                                "releaseYear": {
                                    "__typename": "YearRange",
                                    "year": 2013,
                                    "endYear": null
                                },
                                "releaseDate": {
                                    "__typename": "ReleaseDate",
                                    "month": 11,
                                    "day": 27,
                                    "year": 2013,
                                    "country": {
                                        "id": "US"
                                    },
                                    "restriction": null,
                                    "attributes": [],
                                    "displayableProperty": {
                                        "qualifiersInMarkdownList": null
                                    }
                                },
                                "titleType": {
                                    "__typename": "TitleType",
                                    "id": "movie",
                                    "text": "Movie",
                                    "categories": [
                                        {
                                            "id": "movie",
                                            "text": "Movie",
                                            "value": "movie"
                                        }
                                    ],
                                    "canHaveEpisodes": false,
                                    "isEpisode": false,
                                    "isSeries": false,
                                    "displayableProperty": {
                                        "value": {
                                            "plainText": ""
                                        }
                                    }
                                },
                                "primaryImage": {
                                    "__typename": "Image",
                                    "id": "rm405854208",
                                    "url": "https://m.media-amazon.com/images/M/MV5BMTk5NTEwMzI5OV5BMl5BanBnXkFtZTgwMDQ4ODUwMDE@._V1_.jpg",
                                    "height": 2048,
                                    "width": 1387
                                },
                                "ratingsSummary": {
                                    "aggregateRating": 5.8
                                }
                            },
                            "credit": {
                                "__typename": "Cast",
                                "category": {
                                    "id": "actor",
                                    "text": "Actor"
                                },
                                "characters": [
                                    {
                                        "name": "Chaney"
                                    }
                                ]
                            }
                        }
                    },
                    {
                        "node": {
                            "title": {
                                "__typename": "Title",
                                "id": "tt0107290",
                                "titleText": {
                                    "text": "Jurassic Park",
                                    "isOriginalTitle": true
                                },
                                "originalTitleText": {
                                    "text": "Jurassic Park",
                                    "isOriginalTitle": true
                                },
                                "releaseYear": {
                                    "__typename": "YearRange",
                                    "year": 1993,
                                    "endYear": null
                                },
                                "releaseDate": {
                                    "__typename": "ReleaseDate",
                                    "month": 6,
                                    "day": 11,
                                    "year": 1993,
                                    "country": {
                                        "id": "US"
                                    },
                                    "restriction": null,
                                    "attributes": [],
                                    "displayableProperty": {
                                        "qualifiersInMarkdownList": null
                                    }
                                },
                                "titleType": {
                                    "__typename": "TitleType",
                                    "id": "movie",
                                    "text": "Movie",
                                    "categories": [
                                        {
                                            "id": "movie",
                                            "text": "Movie",
                                            "value": "movie"
                                        }
                                    ],
                                    "canHaveEpisodes": false,
                                    "isEpisode": false,
                                    "isSeries": false,
                                    "displayableProperty": {
                                        "value": {
                                            "plainText": ""
                                        }
                                    }
                                },
                                "primaryImage": {
                                    "__typename": "Image",
                                    "id": "rm3913805824",
                                    "url": "https://m.media-amazon.com/images/M/MV5BMjM2MDgxMDg0Nl5BMl5BanBnXkFtZTgwNTM2OTM5NDE@._V1_.jpg",
                                    "height": 1000,
                                    "width": 667
                                },
                                "ratingsSummary": {
                                    "aggregateRating": 8.2
                                }
                            },
                            "credit": {
                                "__typename": "Cast",
                                "category": {
                                    "id": "actor",
                                    "text": "Actor"
                                },
                                "characters": [
                                    {
                                        "name": "Arnold"
                                    }
                                ]
                            }
                        }
                    },
                    {
                        "node": {
                            "title": {
                                "__typename": "Title",
                                "id": "tt6823368",
                                "titleText": {
                                    "text": "Glass",
                                    "isOriginalTitle": true
                                },
                                "originalTitleText": {
                                    "text": "Glass",
                                    "isOriginalTitle": true
                                },
                                "releaseYear": {
                                    "__typename": "YearRange",
                                    "year": 2019,
                                    "endYear": null
                                },
                                "releaseDate": {
                                    "__typename": "ReleaseDate",
                                    "month": 1,
                                    "day": 18,
                                    "year": 2019,
                                    "country": {
                                        "id": "US"
                                    },
                                    "restriction": null,
                                    "attributes": [],
                                    "displayableProperty": {
                                        "qualifiersInMarkdownList": null
                                    }
                                },
                                "titleType": {
                                    "__typename": "TitleType",
                                    "id": "movie",
                                    "text": "Movie",
                                    "categories": [
                                        {
                                            "id": "movie",
                                            "text": "Movie",
                                            "value": "movie"
                                        }
                                    ],
                                    "canHaveEpisodes": false,
                                    "isEpisode": false,
                                    "isSeries": false,
                                    "displayableProperty": {
                                        "value": {
                                            "plainText": ""
                                        }
                                    }
                                },
                                "primaryImage": {
                                    "__typename": "Image",
                                    "id": "rm2746709504",
                                    "url": "https://m.media-amazon.com/images/M/MV5BMTY1OTA2MjI5OV5BMl5BanBnXkFtZTgwNzkxMjU4NjM@._V1_.jpg",
                                    "height": 1100,
                                    "width": 770
                                },
                                "ratingsSummary": {
                                    "aggregateRating": 6.6
                                }
                            },
                            "credit": {
                                "__typename": "Cast",
                                "category": {
                                    "id": "actor",
                                    "text": "Actor"
                                },
                                "characters": [
                                    {
                                        "name": "Elijah Price"
                                    }
                                ]
                            }
                        }
                    },
                    {
                        "node": {
                            "title": {
                                "__typename": "Title",
                                "id": "tt3606756",
                                "titleText": {
                                    "text": "Incredibles 2",
                                    "isOriginalTitle": true
                                },
                                "originalTitleText": {
                                    "text": "Incredibles 2",
                                    "isOriginalTitle": true
                                },
                                "releaseYear": {
                                    "__typename": "YearRange",
                                    "year": 2018,
                                    "endYear": null
                                },
                                "releaseDate": {
                                    "__typename": "ReleaseDate",
                                    "month": 6,
                                    "day": 15,
                                    "year": 2018,
                                    "country": {
                                        "id": "US"
                                    },
                                    "restriction": null,
                                    "attributes": [],
                                    "displayableProperty": {
                                        "qualifiersInMarkdownList": null
                                    }
                                },
                                "titleType": {
                                    "__typename": "TitleType",
                                    "id": "movie",
                                    "text": "Movie",
                                    "categories": [
                                        {
                                            "id": "movie",
                                            "text": "Movie",
                                            "value": "movie"
                                        }
                                    ],
                                    "canHaveEpisodes": false,
                                    "isEpisode": false,
                                    "isSeries": false,
                                    "displayableProperty": {
                                        "value": {
                                            "plainText": ""
                                        }
                                    }
                                },
                                "primaryImage": {
                                    "__typename": "Image",
                                    "id": "rm985091584",
                                    "url": "https://m.media-amazon.com/images/M/MV5BMTEzNzY0OTg0NTdeQTJeQWpwZ15BbWU4MDU3OTg3MjUz._V1_.jpg",
                                    "height": 1609,
                                    "width": 1086
                                },
                                "ratingsSummary": {
                                    "aggregateRating": 7.5
                                }
                            },
                            "credit": {
                                "__typename": "Cast",
                                "category": {
                                    "id": "actor",
                                    "text": "Actor"
                                },
                                "characters": [
                                    {
                                        "name": "Lucius Best"
                                    },
                                    {
                                        "name": "Frozone"
                                    }
                                ]
                            }
                        }
                    },
                    {
                        "node": {
                            "title": {
                                "__typename": "Title",
                                "id": "tt0227984",
                                "titleText": {
                                    "text": "Formula 51",
                                    "isOriginalTitle": false
                                },
                                "originalTitleText": {
                                    "text": "The 51st State",
                                    "isOriginalTitle": true
                                },
                                "releaseYear": {
                                    "__typename": "YearRange",
                                    "year": 2001,
                                    "endYear": null
                                },
                                "releaseDate": {
                                    "__typename": "ReleaseDate",
                                    "month": 10,
                                    "day": 18,
                                    "year": 2002,
                                    "country": {
                                        "id": "US"
                                    },
                                    "restriction": null,
                                    "attributes": [],
                                    "displayableProperty": {
                                        "qualifiersInMarkdownList": null
                                    }
                                },
                                "titleType": {
                                    "__typename": "TitleType",
                                    "id": "movie",
                                    "text": "Movie",
                                    "categories": [
                                        {
                                            "id": "movie",
                                            "text": "Movie",
                                            "value": "movie"
                                        }
                                    ],
                                    "canHaveEpisodes": false,
                                    "isEpisode": false,
                                    "isSeries": false,
                                    "displayableProperty": {
                                        "value": {
                                            "plainText": ""
                                        }
                                    }
                                },
                                "primaryImage": {
                                    "__typename": "Image",
                                    "id": "rm3031144704",
                                    "url": "https://m.media-amazon.com/images/M/MV5BMTg5NzU4NjEwNV5BMl5BanBnXkFtZTYwNTk4NzM3._V1_.jpg",
                                    "height": 652,
                                    "width": 450
                                },
                                "ratingsSummary": {
                                    "aggregateRating": 6.3
                                }
                            },
                            "credit": {
                                "__typename": "Cast",
                                "category": {
                                    "id": "actor",
                                    "text": "Actor"
                                },
                                "characters": [
                                    {
                                        "name": "Elmo McElroy"
                                    }
                                ]
                            }
                        }
                    }
                ]
            }
        }
    },
    "status": true,
    "message": "Successful"
}